vizier/__init__.py
vizier/pythia.py
vizier/_src/__init__.py
vizier/_src/algorithms/__init__.py
vizier/_src/algorithms/classification/classifiers.py
vizier/_src/algorithms/classification/classifiers_test.py
vizier/_src/algorithms/core/__init__.py
vizier/_src/algorithms/core/abstractions.py
vizier/_src/algorithms/designers/__init__.py
vizier/_src/algorithms/designers/bocs.py
vizier/_src/algorithms/designers/bocs_test.py
vizier/_src/algorithms/designers/cmaes.py
vizier/_src/algorithms/designers/cmaes_test.py
vizier/_src/algorithms/designers/gp_bandit.py
vizier/_src/algorithms/designers/gp_bandit_test.py
vizier/_src/algorithms/designers/gp_ucb_pe.py
vizier/_src/algorithms/designers/gp_ucb_pe_test.py
vizier/_src/algorithms/designers/grid.py
vizier/_src/algorithms/designers/grid_test.py
vizier/_src/algorithms/designers/harmonica.py
vizier/_src/algorithms/designers/harmonica_test.py
vizier/_src/algorithms/designers/quasi_random.py
vizier/_src/algorithms/designers/quasi_random_test.py
vizier/_src/algorithms/designers/random.py
vizier/_src/algorithms/designers/random_test.py
vizier/_src/algorithms/designers/scalarization.py
vizier/_src/algorithms/designers/scalarization_test.py
vizier/_src/algorithms/designers/scalarizing_designer.py
vizier/_src/algorithms/designers/scalarizing_designer_test.py
vizier/_src/algorithms/designers/scheduled_designer.py
vizier/_src/algorithms/designers/scheduled_designer_test.py
vizier/_src/algorithms/designers/scheduled_gp_bandit.py
vizier/_src/algorithms/designers/scheduled_gp_ucb_pe.py
vizier/_src/algorithms/designers/unsafe_as_infeasible_designer.py
vizier/_src/algorithms/designers/unsafe_as_infeasible_designer_test.py
vizier/_src/algorithms/designers/eagle_strategy/eagle_designer_convergence_test.py
vizier/_src/algorithms/designers/eagle_strategy/eagle_simplekd_test.py
vizier/_src/algorithms/designers/eagle_strategy/eagle_strategy.py
vizier/_src/algorithms/designers/eagle_strategy/eagle_strategy_test.py
google_vizier-0.1.24.dist-info/LICENSE
google_vizier-0.1.24.dist-info/METADATA
google_vizier-0.1.24.dist-info/WHEEL
google_vizier-0.1.24.dist-info/top_level.txt
google_vizier-0.1.24.dist-info/RECORD
