Metadata-Version: 2.2
Name: google-vizier
Version: 0.1.24
Summary: Open Source Vizier: Distributed service framework for blackbox optimization and research.
Home-page: https://github.com/google/vizier
Author: Vizier Team
Author-email: oss-vizier-dev@google.com
License: Apache License 2.0
Keywords: ai machine learning hyperparameter blackbox optimization framework
Classifier: Development Status :: 3 - Alpha
Classifier: Intended Audience :: Developers
Classifier: Intended Audience :: Education
Classifier: Intended Audience :: Science/Research
Classifier: License :: OSI Approved :: Apache Software License
Classifier: Programming Language :: Python :: 3
Classifier: Programming Language :: Python :: 3.9
Classifier: Topic :: Scientific/Engineering :: Mathematics
Classifier: Topic :: Software Development :: Libraries :: Python Modules
Classifier: Topic :: Software Development :: Libraries
Requires-Python: >=3.8
License-File: LICENSE
Requires-Dist: attrs>=23.1.0
Requires-Dist: absl-py>=1.0.0
Requires-Dist: numpy>=1.21.5
Requires-Dist: protobuf>=3.6
Requires-Dist: portpicker>=1.3.1
Requires-Dist: grpcio>=1.49.0
Requires-Dist: googleapis-common-protos>=1.56.4
Requires-Dist: sqlalchemy>=1.4
Provides-Extra: jax
Requires-Dist: jax>=0.4.34; extra == "jax"
Requires-Dist: jaxlib>=0.4.34; extra == "jax"
Requires-Dist: jaxopt>=0.8.3; extra == "jax"
Requires-Dist: flax>=0.10.0; extra == "jax"
Requires-Dist: optax>=0.2.3; extra == "jax"
Requires-Dist: chex>=0.1.87; extra == "jax"
Requires-Dist: tfp-nightly[jax]; extra == "jax"
Requires-Dist: equinox==0.11.7; extra == "jax"
Requires-Dist: jaxtyping>=0.2.34; extra == "jax"
Requires-Dist: typeguard<=2.13.3; extra == "jax"
Provides-Extra: tf
Requires-Dist: tensorflow>=2.9.1; extra == "tf"
Provides-Extra: algorithms
Requires-Dist: cvxpy; extra == "algorithms"
Requires-Dist: cvxopt; extra == "algorithms"
Requires-Dist: scikit-learn; extra == "algorithms"
Requires-Dist: evojax; extra == "algorithms"
Requires-Dist: lightgbm; extra == "algorithms"
Provides-Extra: benchmarks
Requires-Dist: matplotlib; extra == "benchmarks"
Requires-Dist: pandas; extra == "benchmarks"
Requires-Dist: ale-py; extra == "benchmarks"
Requires-Dist: nats_bench; extra == "benchmarks"
Requires-Dist: xgboost; extra == "benchmarks"
Requires-Dist: ray[default]; extra == "benchmarks"
Requires-Dist: optproblems==1.3; extra == "benchmarks"
Requires-Dist: diversipy==0.9; extra == "benchmarks"
Provides-Extra: test
Requires-Dist: coverage<=6.4.2,>=4.5; extra == "test"
Requires-Dist: mock<=4.0.3,>=3.0; extra == "test"
Requires-Dist: pytest; extra == "test"
Provides-Extra: all
Requires-Dist: jax>=0.4.34; extra == "all"
Requires-Dist: jaxlib>=0.4.34; extra == "all"
Requires-Dist: jaxopt>=0.8.3; extra == "all"
Requires-Dist: flax>=0.10.0; extra == "all"
Requires-Dist: optax>=0.2.3; extra == "all"
Requires-Dist: chex>=0.1.87; extra == "all"
Requires-Dist: tfp-nightly[jax]; extra == "all"
Requires-Dist: equinox==0.11.7; extra == "all"
Requires-Dist: jaxtyping>=0.2.34; extra == "all"
Requires-Dist: typeguard<=2.13.3; extra == "all"
Requires-Dist: tensorflow>=2.9.1; extra == "all"
Requires-Dist: cvxpy; extra == "all"
Requires-Dist: cvxopt; extra == "all"
Requires-Dist: scikit-learn; extra == "all"
Requires-Dist: evojax; extra == "all"
Requires-Dist: lightgbm; extra == "all"
Requires-Dist: matplotlib; extra == "all"
Requires-Dist: pandas; extra == "all"
Requires-Dist: ale-py; extra == "all"
Requires-Dist: nats_bench; extra == "all"
Requires-Dist: xgboost; extra == "all"
Requires-Dist: ray[default]; extra == "all"
Requires-Dist: optproblems==1.3; extra == "all"
Requires-Dist: diversipy==0.9; extra == "all"
Requires-Dist: coverage<=6.4.2,>=4.5; extra == "all"
Requires-Dist: mock<=4.0.3,>=3.0; extra == "all"
Requires-Dist: pytest; extra == "all"
Dynamic: author
Dynamic: author-email
Dynamic: classifier
Dynamic: description
Dynamic: description-content-type
Dynamic: home-page
Dynamic: keywords
Dynamic: license
Dynamic: provides-extra
Dynamic: requires-dist
Dynamic: requires-python
Dynamic: summary
